CHANGES.rst
CREDITS.rst
LICENSE.rst
MANIFEST.in
README.rst
setup.cfg
setup.py
lizard_map/KRWwaterlichamen_vlakken.shp
lizard_map/__init__.py
lizard_map/adapter.py
lizard_map/admin.py
lizard_map/conf.py
lizard_map/configchecker.py
lizard_map/coordinates.py
lizard_map/dateperiods.py
lizard_map/daterange.py
lizard_map/datewidget.py
lizard_map/exceptions.py
lizard_map/fields.py
lizard_map/forms.py
lizard_map/layers.py
lizard_map/lizard_widgets.py
lizard_map/mapnik_helper.py
lizard_map/matplotlib_settings.py
lizard_map/middleware.py
lizard_map/models.py
lizard_map/operations.py
lizard_map/profilemiddleware.py
lizard_map/symbol_manager.py
lizard_map/test_models.py
lizard_map/test_templatetags.py
lizard_map/testsettings.py
lizard_map/urls.py
lizard_map/utility.py
lizard_map/views.py
lizard_map/workspace.py
lizard_map.egg-info/PKG-INFO
lizard_map.egg-info/SOURCES.txt
lizard_map.egg-info/dependency_links.txt
lizard_map.egg-info/entry_points.txt
lizard_map.egg-info/not-zip-safe
lizard_map.egg-info/requires.txt
lizard_map.egg-info/top_level.txt
lizard_map/api/__init__.py
lizard_map/api/handlers.py
lizard_map/api/urls.py
lizard_map/fixtures/background_maps.json
lizard_map/icons/brug.png
lizard_map/icons/brug_mask.png
lizard_map/icons/buoy.png
lizard_map/icons/buoy_mask.png
lizard_map/icons/consluis.png
lizard_map/icons/consluis_mask.png
lizard_map/icons/duiker.png
lizard_map/icons/duiker_mask.png
lizard_map/icons/empty.png
lizard_map/icons/empty_mask.png
lizard_map/icons/gemaal.png
lizard_map/icons/gemaal_mask.png
lizard_map/icons/ghost.png
lizard_map/icons/grid.png
lizard_map/icons/grid_mask.png
lizard_map/icons/hevel.png
lizard_map/icons/hevel_mask.png
lizard_map/icons/inlaat.png
lizard_map/icons/inlaat_mask.png
lizard_map/icons/line.png
lizard_map/icons/mask.png
lizard_map/icons/meetpuntBWS.png
lizard_map/icons/meetpuntBWS_mask.png
lizard_map/icons/meetpuntNeerslag.png
lizard_map/icons/meetpuntNeerslag_mask.png
lizard_map/icons/meetpuntPeil.png
lizard_map/icons/meetpuntPeil_mask.png
lizard_map/icons/neerslagstation.png
lizard_map/icons/neerslagstation_mask.png
lizard_map/icons/onderbemaling.png
lizard_map/icons/onderbemaling_mask.png
lizard_map/icons/overstort.png
lizard_map/icons/overstort_mask.png
