Metadata-Version: 1.1
Name: lizard-map
Version: 5.4
Summary: Basic map setup for lizard web sites
Home-page: http://www.nelen-schuurmans.nl/lizard/
Author: Reinout van Rees
Author-email: reinout.vanrees@nelen-schuurmans.nl
License: LGPL
Platform: UNKNOWN
Classifier: Programming Language :: Python
Classifier: Framework :: Django
